[
  {
    "round": 1,
    "phase": 1,
    "table": 1,
    "winner": "zhi_ye",
    "player1": "mercur",
    "player2": "zhi_ye"
  },
  {
    "round": 1,
    "phase": 1,
    "table": 2,
    "winner": "matcha",
    "player1": "matcha",
    "player2": "zabaniya"
  },
  {
    "round": 1,
    "phase": 1,
    "table": 3,
    "winner": "matiasrivera",
    "player1": "kingdallas",
    "player2": "matiasrivera"
  },
  {
    "round": 1,
    "phase": 1,
    "table": 4,
    "winner": "yanmaru",
    "player1": "junior_lo",
    "player2": "yanmaru"
  },
  {
    "round": 1,
    "phase": 1,
    "table": 5,
    "winner": "amoex",
    "player1": "amoex",
    "player2": "s_p203"
  },
  {
    "round": 1,
    "phase": 1,
    "table": 6,
    "winner": "kinkakuj",
    "player1": "jeyksu",
    "player2": "kinkakuj"
  },
  {
    "round": 1,
    "phase": 1,
    "table": 7,
    "winner": "vladd",
    "player1": "giantturd625",
    "player2": "vladd"
  },
  {
    "round": 1,
    "phase": 1,
    "table": 8,
    "winner": "super_peace",
    "player1": "super_peace",
    "player2": "x2kuro"
  },
  {
    "round": 1,
    "phase": 1,
    "table": 9,
    "winner": "mami",
    "player1": "mami",
    "player2": "ulico"
  },
  {
    "round": 1,
    "phase": 1,
    "table": 10,
    "winner": "lemka",
    "player1": "lemka",
    "player2": "skkun"
  },
  {
    "round": 1,
    "phase": 1,
    "table": 11,
    "winner": "die_kampfstube",
    "player1": "die_kampfstube",
    "player2": "senjupsyduck"
  },
  {
    "round": 1,
    "phase": 1,
    "table": 12,
    "winner": "babyeatingbaby",
    "player1": "babyeatingbaby",
    "player2": "wingcheng"
  },
  {
    "round": 1,
    "phase": 1,
    "table": 13,
    "winner": "joony",
    "player1": "lv80mewtwo",
    "player2": "joony"
  },
  {
    "round": 1,
    "phase": 1,
    "table": 14,
    "winner": "kaptenzz",
    "player1": "kaptenzz",
    "player2": "darcklife"
  },
  {
    "round": 1,
    "phase": 1,
    "table": 15,
    "winner": "hyz",
    "player1": "hyz",
    "player2": "ryoutadika"
  },
  {
    "round": 1,
    "phase": 1,
    "table": 16,
    "winner": "slade4000",
    "player1": "kingmistapnw",
    "player2": "slade4000"
  },
  {
    "round": 1,
    "phase": 1,
    "table": 17,
    "winner": -1,
    "player1": "mastersnow101",
    "player2": "monkeydjaylen"
  },
  {
    "round": 1,
    "phase": 1,
    "table": 18,
    "winner": "feraldoto",
    "player1": "semoponume",
    "player2": "feraldoto"
  },
  {
    "round": 1,
    "phase": 1,
    "table": 19,
    "winner": "alpha2005",
    "player1": "loganthorne",
    "player2": "alpha2005"
  },
  {
    "round": 1,
    "phase": 1,
    "table": 20,
    "winner": "hrsnfbrn",
    "player1": "fukuda",
    "player2": "hrsnfbrn"
  },
  {
    "round": 1,
    "phase": 1,
    "table": 21,
    "winner": "and",
    "player1": "and",
    "player2": "tong_java_island"
  },
  {
    "round": 1,
    "phase": 1,
    "table": 22,
    "winner": "dr_in_d_go",
    "player1": "hojinar",
    "player2": "dr_in_d_go"
  },
  {
    "round": 1,
    "phase": 1,
    "table": 23,
    "winner": "anjasmara19",
    "player1": "anjasmara19",
    "player2": "julian999"
  },
  {
    "round": 1,
    "phase": 1,
    "table": 24,
    "winner": "andikaaa",
    "player1": "andikaaa",
    "player2": "hancockay"
  },
  {
    "round": 1,
    "phase": 1,
    "table": 25,
    "winner": "yoshilou323",
    "player1": "yoshilou323",
    "player2": "mochizoyu"
  },
  {
    "round": 1,
    "phase": 1,
    "table": 26,
    "winner": "arrr",
    "player1": "arrr",
    "player2": "kironkiron"
  },
  {
    "round": 1,
    "phase": 1,
    "table": 27,
    "winner": "sparadrap",
    "player1": "aimonn",
    "player2": "sparadrap"
  },
  {
    "round": 1,
    "phase": 1,
    "table": 28,
    "winner": "chueen",
    "player1": "shinm",
    "player2": "chueen"
  },
  {
    "round": 1,
    "phase": 1,
    "table": 29,
    "winner": "tomohero",
    "player1": "thechocoloveh",
    "player2": "tomohero"
  },
  {
    "round": 1,
    "phase": 1,
    "table": 30,
    "winner": "oreight",
    "player1": "oreight",
    "player2": "rinda_man"
  },
  {
    "round": 1,
    "phase": 1,
    "table": 31,
    "winner": "iruragin",
    "player1": "iruragin",
    "player2": "adrian_pale"
  },
  {
    "round": 1,
    "phase": 1,
    "table": 32,
    "winner": "taugh",
    "player1": "taugh",
    "player2": "wival"
  },
  {
    "round": 1,
    "phase": 1,
    "table": 33,
    "winner": "gabb320",
    "player1": "zzloquillozz",
    "player2": "gabb320"
  },
  {
    "round": 1,
    "phase": 1,
    "table": 34,
    "winner": "levajah",
    "player1": "gcerbat",
    "player2": "levajah"
  },
  {
    "round": 1,
    "phase": 1,
    "table": 35,
    "winner": "tuborizm",
    "player1": "dardarburr",
    "player2": "tuborizm"
  },
  {
    "round": 1,
    "phase": 1,
    "table": 36,
    "winner": "taata",
    "player1": "taata",
    "player2": "a11seeingeye"
  },
  {
    "round": 1,
    "phase": 1,
    "table": 37,
    "winner": "sirabosi",
    "player1": "danston",
    "player2": "sirabosi"
  },
  {
    "round": 1,
    "phase": 1,
    "table": 38,
    "winner": "bayashi",
    "player1": "kingzano",
    "player2": "bayashi"
  },
  {
    "round": 1,
    "phase": 1,
    "table": 39,
    "winner": "reeyyy09",
    "player1": "reeyyy09",
    "player2": "berlin"
  },
  {
    "round": 1,
    "phase": 1,
    "table": 40,
    "winner": "antacumbo",
    "player1": "antacumbo",
    "player2": "neoandrev"
  },
  {
    "round": 1,
    "phase": 1,
    "table": 41,
    "winner": "number_c32",
    "player1": "caspersnooker",
    "player2": "number_c32"
  },
  {
    "round": 1,
    "phase": 1,
    "table": 42,
    "winner": "epiktommy",
    "player1": "epiktommy",
    "player2": "god16888"
  },
  {
    "round": 2,
    "phase": 1,
    "table": 1,
    "winner": "number_c32",
    "player1": "number_c32",
    "player2": "vladd"
  },
  {
    "round": 2,
    "phase": 1,
    "table": 2,
    "winner": "matcha",
    "player1": "kaptenzz",
    "player2": "matcha"
  },
  {
    "round": 2,
    "phase": 1,
    "table": 3,
    "winner": "yoshilou323",
    "player1": "yoshilou323",
    "player2": "antacumbo"
  },
  {
    "round": 2,
    "phase": 1,
    "table": 4,
    "winner": "babyeatingbaby",
    "player1": "die_kampfstube",
    "player2": "babyeatingbaby"
  },
  {
    "round": 2,
    "phase": 1,
    "table": 5,
    "winner": "reeyyy09",
    "player1": "taata",
    "player2": "reeyyy09"
  },
  {
    "round": 2,
    "phase": 1,
    "table": 6,
    "winner": "sparadrap",
    "player1": "hrsnfbrn",
    "player2": "sparadrap"
  },
  {
    "round": 2,
    "phase": 1,
    "table": 7,
    "winner": "arrr",
    "player1": "arrr",
    "player2": "andikaaa"
  },
  {
    "round": 2,
    "phase": 1,
    "table": 8,
    "winner": "super_peace",
    "player1": "matiasrivera",
    "player2": "super_peace"
  },
  {
    "round": 2,
    "phase": 1,
    "table": 9,
    "winner": "slade4000",
    "player1": "slade4000",
    "player2": "tuborizm"
  },
  {
    "round": 2,
    "phase": 1,
    "table": 10,
    "winner": "hyz",
    "player1": "hyz",
    "player2": "lemka"
  },
  {
    "round": 2,
    "phase": 1,
    "table": 11,
    "winner": "levajah",
    "player1": "sirabosi",
    "player2": "levajah"
  },
  {
    "round": 2,
    "phase": 1,
    "table": 12,
    "winner": "epiktommy",
    "player1": "epiktommy",
    "player2": "gabb320"
  },
  {
    "round": 2,
    "phase": 1,
    "table": 13,
    "winner": "mami",
    "player1": "mami",
    "player2": "chueen"
  },
  {
    "round": 2,
    "phase": 1,
    "table": 14,
    "winner": "dr_in_d_go",
    "player1": "dr_in_d_go",
    "player2": "bayashi"
  },
  {
    "round": 2,
    "phase": 1,
    "table": 15,
    "winner": "kinkakuj",
    "player1": "kinkakuj",
    "player2": "tomohero"
  },
  {
    "round": 2,
    "phase": 1,
    "table": 16,
    "winner": "zhi_ye",
    "player1": "taugh",
    "player2": "zhi_ye"
  },
  {
    "round": 2,
    "phase": 1,
    "table": 17,
    "winner": "iruragin",
    "player1": "iruragin",
    "player2": "feraldoto"
  },
  {
    "round": 2,
    "phase": 1,
    "table": 18,
    "winner": "oreight",
    "player1": "oreight",
    "player2": "anjasmara19"
  },
  {
    "round": 2,
    "phase": 1,
    "table": 19,
    "winner": "joony",
    "player1": "and",
    "player2": "joony"
  },
  {
    "round": 2,
    "phase": 1,
    "table": 20,
    "winner": "amoex",
    "player1": "amoex",
    "player2": "alpha2005"
  },
  {
    "round": 2,
    "phase": 1,
    "table": 21,
    "winner": "yanmaru",
    "player1": "yanmaru",
    "player2": "neoandrev"
  },
  {
    "round": 2,
    "phase": 1,
    "table": 22,
    "winner": -1,
    "player1": "darcklife",
    "player2": "x2kuro"
  },
  {
    "round": 2,
    "phase": 1,
    "table": 23,
    "winner": -1,
    "player1": "hojinar",
    "player2": "wival"
  },
  {
    "round": 2,
    "phase": 1,
    "table": 24,
    "winner": "semoponume",
    "player1": "semoponume",
    "player2": "zzloquillozz"
  },
  {
    "round": 2,
    "phase": 1,
    "table": 25,
    "winner": "berlin",
    "player1": "caspersnooker",
    "player2": "berlin"
  },
  {
    "round": 2,
    "phase": 1,
    "table": 26,
    "winner": "rinda_man",
    "player1": "wingcheng",
    "player2": "rinda_man"
  },
  {
    "round": 2,
    "phase": 1,
    "table": 27,
    "winner": "thechocoloveh",
    "player1": "monkeydjaylen",
    "player2": "thechocoloveh"
  },
  {
    "round": 2,
    "phase": 1,
    "table": 28,
    "winner": "skkun",
    "player1": "skkun",
    "player2": "dardarburr"
  },
  {
    "round": 2,
    "phase": 1,
    "table": 29,
    "winner": "jeyksu",
    "player1": "jeyksu",
    "player2": "god16888"
  },
  {
    "round": 2,
    "phase": 1,
    "table": 30,
    "winner": "kironkiron",
    "player1": "kironkiron",
    "player2": "adrian_pale"
  },
  {
    "round": 2,
    "phase": 1,
    "table": 31,
    "winner": -1,
    "player1": "kingdallas",
    "player2": "kingmistapnw"
  },
  {
    "round": 2,
    "phase": 1,
    "table": 32,
    "winner": "aimonn",
    "player1": "aimonn",
    "player2": "senjupsyduck"
  },
  {
    "round": 2,
    "phase": 1,
    "table": 33,
    "winner": "junior_lo",
    "player1": "junior_lo",
    "player2": "loganthorne"
  },
  {
    "round": 2,
    "phase": 1,
    "table": 34,
    "winner": "ryoutadika",
    "player1": "ryoutadika",
    "player2": "mastersnow101"
  },
  {
    "round": 2,
    "phase": 1,
    "table": 35,
    "winner": "danston",
    "player1": "danston",
    "player2": "a11seeingeye"
  },
  {
    "round": 2,
    "phase": 1,
    "table": 36,
    "winner": "julian999",
    "player1": "julian999",
    "player2": "zabaniya"
  },
  {
    "round": 2,
    "phase": 1,
    "table": 37,
    "winner": "tong_java_island",
    "player1": "gcerbat",
    "player2": "tong_java_island"
  },
  {
    "round": 2,
    "phase": 1,
    "table": 38,
    "winner": "hancockay",
    "player1": "shinm",
    "player2": "hancockay"
  },
  {
    "round": 2,
    "phase": 1,
    "table": 39,
    "winner": "fukuda",
    "player1": "fukuda",
    "player2": "ulico"
  },
  {
    "round": 3,
    "phase": 1,
    "table": 1,
    "winner": "dr_in_d_go",
    "player1": "yoshilou323",
    "player2": "dr_in_d_go"
  },
  {
    "round": 3,
    "phase": 1,
    "table": 2,
    "winner": "arrr",
    "player1": "amoex",
    "player2": "arrr"
  },
  {
    "round": 3,
    "phase": 1,
    "table": 3,
    "winner": "yanmaru",
    "player1": "yanmaru",
    "player2": "epiktommy"
  },
  {
    "round": 3,
    "phase": 1,
    "table": 4,
    "winner": "mami",
    "player1": "mami",
    "player2": "babyeatingbaby"
  },
  {
    "round": 3,
    "phase": 1,
    "table": 5,
    "winner": "super_peace",
    "player1": "sparadrap",
    "player2": "super_peace"
  },
  {
    "round": 3,
    "phase": 1,
    "table": 6,
    "winner": "levajah",
    "player1": "levajah",
    "player2": "number_c32"
  },
  {
    "round": 3,
    "phase": 1,
    "table": 7,
    "winner": "zhi_ye",
    "player1": "iruragin",
    "player2": "zhi_ye"
  },
  {
    "round": 3,
    "phase": 1,
    "table": 8,
    "winner": "kinkakuj",
    "player1": "joony",
    "player2": "kinkakuj"
  },
  {
    "round": 3,
    "phase": 1,
    "table": 9,
    "winner": "oreight",
    "player1": "oreight",
    "player2": "hyz"
  },
  {
    "round": 3,
    "phase": 1,
    "table": 10,
    "winner": "slade4000",
    "player1": "slade4000",
    "player2": "matcha"
  },
  {
    "round": 3,
    "phase": 1,
    "table": 11,
    "winner": "aimonn",
    "player1": "aimonn",
    "player2": "rinda_man"
  },
  {
    "round": 3,
    "phase": 1,
    "table": 12,
    "winner": "andikaaa",
    "player1": "andikaaa",
    "player2": "lemka"
  },
  {
    "round": 3,
    "phase": 1,
    "table": 13,
    "winner": "vladd",
    "player1": "vladd",
    "player2": "kaptenzz"
  },
  {
    "round": 3,
    "phase": 1,
    "table": 14,
    "winner": "taugh",
    "player1": "skkun",
    "player2": "taugh"
  },
  {
    "round": 3,
    "phase": 1,
    "table": 15,
    "winner": "hrsnfbrn",
    "player1": "hrsnfbrn",
    "player2": "chueen"
  },
  {
    "round": 3,
    "phase": 1,
    "table": 16,
    "winner": "tuborizm",
    "player1": "tong_java_island",
    "player2": "tuborizm"
  },
  {
    "round": 3,
    "phase": 1,
    "table": 17,
    "winner": "fukuda",
    "player1": "ryoutadika",
    "player2": "fukuda"
  },
  {
    "round": 3,
    "phase": 1,
    "table": 18,
    "winner": "anjasmara19",
    "player1": "anjasmara19",
    "player2": "sirabosi"
  },
  {
    "round": 3,
    "phase": 1,
    "table": 19,
    "winner": "gabb320",
    "player1": "gabb320",
    "player2": "jeyksu"
  },
  {
    "round": 3,
    "phase": 1,
    "table": 20,
    "winner": "semoponume",
    "player1": "and",
    "player2": "semoponume"
  },
  {
    "round": 3,
    "phase": 1,
    "table": 21,
    "winner": "berlin",
    "player1": "danston",
    "player2": "berlin"
  },
  {
    "round": 3,
    "phase": 1,
    "table": 22,
    "winner": "kironkiron",
    "player1": "kironkiron",
    "player2": "alpha2005"
  },
  {
    "round": 3,
    "phase": 1,
    "table": 23,
    "winner": "bayashi",
    "player1": "bayashi",
    "player2": "tomohero"
  },
  {
    "round": 3,
    "phase": 1,
    "table": 24,
    "winner": "matiasrivera",
    "player1": "die_kampfstube",
    "player2": "matiasrivera"
  },
  {
    "round": 3,
    "phase": 1,
    "table": 25,
    "winner": "feraldoto",
    "player1": "feraldoto",
    "player2": "hancockay"
  },
  {
    "round": 3,
    "phase": 1,
    "table": 26,
    "winner": "thechocoloveh",
    "player1": "julian999",
    "player2": "thechocoloveh"
  },
  {
    "round": 3,
    "phase": 1,
    "table": 27,
    "winner": "junior_lo",
    "player1": "antacumbo",
    "player2": "junior_lo"
  },
  {
    "round": 3,
    "phase": 1,
    "table": 28,
    "winner": -1,
    "player1": "shinm",
    "player2": "kingmistapnw"
  },
  {
    "round": 3,
    "phase": 1,
    "table": 29,
    "winner": "zabaniya",
    "player1": "monkeydjaylen",
    "player2": "zabaniya"
  },
  {
    "round": 3,
    "phase": 1,
    "table": 30,
    "winner": -1,
    "player1": "hojinar",
    "player2": "kingdallas"
  },
  {
    "round": 3,
    "phase": 1,
    "table": 31,
    "winner": "ulico",
    "player1": "ulico",
    "player2": "a11seeingeye"
  },
  {
    "round": 3,
    "phase": 1,
    "table": 32,
    "winner": -1,
    "player1": "x2kuro",
    "player2": "mastersnow101"
  },
  {
    "round": 3,
    "phase": 1,
    "table": 33,
    "winner": "caspersnooker",
    "player1": "darcklife",
    "player2": "caspersnooker"
  },
  {
    "round": 3,
    "phase": 1,
    "table": 34,
    "winner": -1,
    "player1": "loganthorne",
    "player2": "zzloquillozz"
  },
  {
    "round": 3,
    "phase": 1,
    "table": 35,
    "winner": -1,
    "player1": "wingcheng",
    "player2": "adrian_pale"
  },
  {
    "round": 3,
    "phase": 1,
    "table": 36,
    "winner": -1,
    "player1": "dardarburr",
    "player2": "neoandrev"
  },
  {
    "round": 3,
    "phase": 1,
    "table": 37,
    "winner": "senjupsyduck",
    "player1": "senjupsyduck"
  },
  {
    "round": 4,
    "phase": 1,
    "table": 1,
    "winner": "arrr",
    "player1": "levajah",
    "player2": "arrr"
  },
  {
    "round": 4,
    "phase": 1,
    "table": 2,
    "winner": "dr_in_d_go",
    "player1": "dr_in_d_go",
    "player2": "oreight"
  },
  {
    "round": 4,
    "phase": 1,
    "table": 3,
    "winner": "yanmaru",
    "player1": "mami",
    "player2": "yanmaru"
  },
  {
    "round": 4,
    "phase": 1,
    "table": 4,
    "winner": "zhi_ye",
    "player1": "kinkakuj",
    "player2": "zhi_ye"
  },
  {
    "round": 4,
    "phase": 1,
    "table": 5,
    "winner": "slade4000",
    "player1": "super_peace",
    "player2": "slade4000"
  },
  {
    "round": 4,
    "phase": 1,
    "table": 6,
    "winner": "semoponume",
    "player1": "bayashi",
    "player2": "semoponume"
  },
  {
    "round": 4,
    "phase": 1,
    "table": 7,
    "winner": "kironkiron",
    "player1": "kironkiron",
    "player2": "feraldoto"
  },
  {
    "round": 4,
    "phase": 1,
    "table": 8,
    "winner": "thechocoloveh",
    "player1": "thechocoloveh",
    "player2": "epiktommy"
  },
  {
    "round": 4,
    "phase": 1,
    "table": 9,
    "winner": "gabb320",
    "player1": "gabb320",
    "player2": "hrsnfbrn"
  },
  {
    "round": 4,
    "phase": 1,
    "table": 10,
    "winner": "andikaaa",
    "player1": "anjasmara19",
    "player2": "andikaaa"
  },
  {
    "round": 4,
    "phase": 1,
    "table": 11,
    "winner": "aimonn",
    "player1": "aimonn",
    "player2": "number_c32"
  },
  {
    "round": 4,
    "phase": 1,
    "table": 12,
    "winner": "tuborizm",
    "player1": "joony",
    "player2": "tuborizm"
  },
  {
    "round": 4,
    "phase": 1,
    "table": 13,
    "winner": "amoex",
    "player1": "amoex",
    "player2": "iruragin"
  },
  {
    "round": 4,
    "phase": 1,
    "table": 14,
    "winner": "yoshilou323",
    "player1": "vladd",
    "player2": "yoshilou323"
  },
  {
    "round": 4,
    "phase": 1,
    "table": 15,
    "winner": "sparadrap",
    "player1": "matiasrivera",
    "player2": "sparadrap"
  },
  {
    "round": 4,
    "phase": 1,
    "table": 16,
    "winner": "fukuda",
    "player1": "fukuda",
    "player2": "taugh"
  },
  {
    "round": 4,
    "phase": 1,
    "table": 17,
    "winner": "berlin",
    "player1": "berlin",
    "player2": "matcha"
  },
  {
    "round": 4,
    "phase": 1,
    "table": 18,
    "winner": "junior_lo",
    "player1": "hyz",
    "player2": "junior_lo"
  },
  {
    "round": 4,
    "phase": 1,
    "table": 19,
    "winner": "kaptenzz",
    "player1": "danston",
    "player2": "kaptenzz"
  },
  {
    "round": 4,
    "phase": 1,
    "table": 20,
    "winner": "ulico",
    "player1": "ryoutadika",
    "player2": "ulico"
  },
  {
    "round": 4,
    "phase": 1,
    "table": 21,
    "winner": "jeyksu",
    "player1": "skkun",
    "player2": "jeyksu"
  },
  {
    "round": 4,
    "phase": 1,
    "table": 22,
    "winner": "hancockay",
    "player1": "antacumbo",
    "player2": "hancockay"
  },
  {
    "round": 4,
    "phase": 1,
    "table": 23,
    "winner": "zabaniya",
    "player1": "zabaniya",
    "player2": "tong_java_island"
  },
  {
    "round": 4,
    "phase": 1,
    "table": 24,
    "winner": "julian999",
    "player1": "alpha2005",
    "player2": "julian999"
  },
  {
    "round": 4,
    "phase": 1,
    "table": 25,
    "winner": "chueen",
    "player1": "senjupsyduck",
    "player2": "chueen"
  },
  {
    "round": 4,
    "phase": 1,
    "table": 26,
    "winner": -1,
    "player1": "caspersnooker",
    "player2": "kingmistapnw"
  },
  {
    "round": 4,
    "phase": 1,
    "table": 27,
    "winner": -1,
    "player1": "hojinar",
    "player2": "shinm"
  },
  {
    "round": 4,
    "phase": 1,
    "table": 28,
    "winner": "dardarburr",
    "player1": "x2kuro",
    "player2": "dardarburr"
  },
  {
    "round": 4,
    "phase": 1,
    "table": 29,
    "winner": -1,
    "player1": "mastersnow101",
    "player2": "darcklife"
  },
  {
    "round": 4,
    "phase": 1,
    "table": 30,
    "winner": -1,
    "player1": "adrian_pale",
    "player2": "monkeydjaylen"
  },
  {
    "round": 4,
    "phase": 1,
    "table": 31,
    "winner": -1,
    "player1": "loganthorne",
    "player2": "wingcheng"
  },
  {
    "round": 4,
    "phase": 1,
    "table": 32,
    "winner": -1,
    "player1": "neoandrev",
    "player2": "zzloquillozz"
  },
  {
    "round": 4,
    "phase": 1,
    "table": 33,
    "winner": "kingdallas",
    "player1": "kingdallas"
  },
  {
    "round": 5,
    "phase": 1,
    "table": 1,
    "winner": "arrr",
    "player1": "arrr",
    "player2": "zhi_ye"
  },
  {
    "round": 5,
    "phase": 1,
    "table": 2,
    "winner": 0,
    "player1": "slade4000",
    "player2": "yanmaru"
  },
  {
    "round": 5,
    "phase": 1,
    "table": 3,
    "winner": "dr_in_d_go",
    "player1": "dr_in_d_go",
    "player2": "junior_lo"
  },
  {
    "round": 5,
    "phase": 1,
    "table": 4,
    "winner": "thechocoloveh",
    "player1": "oreight",
    "player2": "thechocoloveh"
  },
  {
    "round": 5,
    "phase": 1,
    "table": 5,
    "winner": "andikaaa",
    "player1": "aimonn",
    "player2": "andikaaa"
  },
  {
    "round": 5,
    "phase": 1,
    "table": 6,
    "winner": "fukuda",
    "player1": "gabb320",
    "player2": "fukuda"
  },
  {
    "round": 5,
    "phase": 1,
    "table": 7,
    "winner": "kironkiron",
    "player1": "kironkiron",
    "player2": "amoex"
  },
  {
    "round": 5,
    "phase": 1,
    "table": 8,
    "winner": "sparadrap",
    "player1": "sparadrap",
    "player2": "berlin"
  },
  {
    "round": 5,
    "phase": 1,
    "table": 9,
    "winner": "super_peace",
    "player1": "yoshilou323",
    "player2": "super_peace"
  },
  {
    "round": 5,
    "phase": 1,
    "table": 10,
    "winner": "kinkakuj",
    "player1": "semoponume",
    "player2": "kinkakuj"
  },
  {
    "round": 5,
    "phase": 1,
    "table": 11,
    "winner": "mami",
    "player1": "mami",
    "player2": "tuborizm"
  },
  {
    "round": 5,
    "phase": 1,
    "table": 12,
    "winner": "levajah",
    "player1": "levajah",
    "player2": "hancockay"
  },
  {
    "round": 5,
    "phase": 1,
    "table": 13,
    "winner": "anjasmara19",
    "player1": "anjasmara19",
    "player2": "joony"
  },
  {
    "round": 5,
    "phase": 1,
    "table": 14,
    "winner": "kaptenzz",
    "player1": "ulico",
    "player2": "kaptenzz"
  },
  {
    "round": 5,
    "phase": 1,
    "table": 15,
    "winner": "jeyksu",
    "player1": "jeyksu",
    "player2": "zabaniya"
  },
  {
    "round": 5,
    "phase": 1,
    "table": 16,
    "winner": "number_c32",
    "player1": "hrsnfbrn",
    "player2": "number_c32"
  },
  {
    "round": 5,
    "phase": 1,
    "table": 17,
    "winner": "chueen",
    "player1": "chueen",
    "player2": "julian999"
  },
  {
    "round": 5,
    "phase": 1,
    "table": 18,
    "winner": "epiktommy",
    "player1": "epiktommy",
    "player2": "vladd"
  },
  {
    "round": 5,
    "phase": 1,
    "table": 19,
    "winner": -1,
    "player1": "caspersnooker",
    "player2": "senjupsyduck"
  },
  {
    "round": 5,
    "phase": 1,
    "table": 20,
    "winner": -1,
    "player1": "alpha2005",
    "player2": "skkun"
  },
  {
    "round": 5,
    "phase": 1,
    "table": 21,
    "winner": -1,
    "player1": "ryoutadika",
    "player2": "kingdallas"
  },
  {
    "round": 5,
    "phase": 1,
    "table": 22,
    "winner": "tong_java_island",
    "player1": "antacumbo",
    "player2": "tong_java_island"
  },
  {
    "round": 5,
    "phase": 1,
    "table": 23,
    "winner": "danston",
    "player1": "dardarburr",
    "player2": "danston"
  },
  {
    "round": 5,
    "phase": 1,
    "table": 24,
    "winner": -1,
    "player1": "darcklife",
    "player2": "kingmistapnw"
  },
  {
    "round": 5,
    "phase": 1,
    "table": 25,
    "winner": -1,
    "player1": "wingcheng",
    "player2": "x2kuro"
  },
  {
    "round": 5,
    "phase": 1,
    "table": 26,
    "winner": -1,
    "player1": "zzloquillozz",
    "player2": "mastersnow101"
  },
  {
    "round": 5,
    "phase": 1,
    "table": 27,
    "winner": -1,
    "player1": "shinm",
    "player2": "adrian_pale"
  },
  {
    "round": 5,
    "phase": 1,
    "table": 28,
    "winner": -1,
    "player1": "loganthorne",
    "player2": "neoandrev"
  },
  {
    "round": 5,
    "phase": 1,
    "table": 29,
    "winner": "hojinar",
    "player1": "hojinar"
  },
  {
    "phase": 2,
    "round": 6,
    "winner": "mami",
    "match": "T4-1",
    "player1": "arrr",
    "player2": "mami"
  },
  {
    "phase": 2,
    "round": 6,
    "winner": "yanmaru",
    "match": "T8-4",
    "player1": "yanmaru",
    "player2": "zhi_ye"
  },
  {
    "phase": 2,
    "round": 6,
    "winner": "arrr",
    "match": "T8-1",
    "player1": "arrr",
    "player2": "andikaaa"
  },
  {
    "phase": 2,
    "round": 6,
    "winner": "yanmaru",
    "match": "T2-1",
    "player1": "mami",
    "player2": "yanmaru"
  },
  {
    "phase": 2,
    "round": 6,
    "winner": "yanmaru",
    "match": "T4-2",
    "player1": "dr_in_d_go",
    "player2": "yanmaru"
  },
  {
    "phase": 2,
    "round": 6,
    "winner": "dr_in_d_go",
    "match": "T8-3",
    "player1": "dr_in_d_go",
    "player2": "super_peace"
  },
  {
    "phase": 2,
    "round": 6,
    "winner": "mami",
    "match": "T8-2",
    "player1": "slade4000",
    "player2": "mami"
  }
]